aesdecrypt/__init__.py
aesdecrypt/cryptojs.py
decrypt/__init__.py
decrypt/cryptojs-aes.py
decrypt/cryptojs.py
decrypt/utils.py
cryptojsaesdecrypt-0.0.3.dist-info/METADATA
cryptojsaesdecrypt-0.0.3.dist-info/WHEEL
cryptojsaesdecrypt-0.0.3.dist-info/top_level.txt
cryptojsaesdecrypt-0.0.3.dist-info/RECORD
