Metadata-Version: 2.1
Name: cryptojsaesdecrypt
Version: 0.0.3
Summary: Decrypt cryptojs encrytped ciphers
Home-page: https://github.com/limistah/cryptojs-decrypt
Author: Aleem Isiaka
Author-email: aleemisiaka@gmail.com
License: MIT
Project-URL: Bug Tracker, https://github.com/limistah/cryptojsaesdecryptissues
Platform: UNKNOWN
Classifier: Intended Audience :: Developers
Classifier: Topic :: Software Development :: Build Tools
Classifier: License :: OSI Approved :: MIT License
Classifier: Programming Language :: Python :: 3
Classifier: Programming Language :: Python :: 3.4
Classifier: Programming Language :: Python :: 3.5
Classifier: Programming Language :: Python :: 3.6
Requires-Python: >=3
Requires-Dist: pycryptodome
